ofa/__init__.py
ofa/model_zoo.py
ofa/imagenet_classification/__init__.py
ofa/imagenet_classification/data_providers/__init__.py
ofa/imagenet_classification/data_providers/base_provider.py
ofa/imagenet_classification/data_providers/imagenet.py
ofa/imagenet_classification/elastic_nn/__init__.py
ofa/imagenet_classification/elastic_nn/utils.py
ofa/imagenet_classification/elastic_nn/modules/__init__.py
ofa/imagenet_classification/elastic_nn/modules/dynamic_layers.py
ofa/imagenet_classification/elastic_nn/modules/dynamic_op.py
ofa/imagenet_classification/elastic_nn/networks/__init__.py
ofa/imagenet_classification/elastic_nn/networks/ofa_mbv3.py
ofa/imagenet_classification/elastic_nn/networks/ofa_proxyless.py
ofa/imagenet_classification/elastic_nn/networks/ofa_resnets.py
ofa/imagenet_classification/elastic_nn/training/__init__.py
ofa/imagenet_classification/elastic_nn/training/progressive_shrinking.py
ofa/imagenet_classification/networks/__init__.py
ofa/imagenet_classification/networks/mobilenet_v3.py
ofa/imagenet_classification/networks/proxyless_nets.py
ofa/imagenet_classification/networks/resnets.py
ofa/imagenet_classification/run_manager/__init__.py
ofa/imagenet_classification/run_manager/distributed_run_manager.py
ofa/imagenet_classification/run_manager/run_config.py
ofa/imagenet_classification/run_manager/run_manager.py
ofa/nas/__init__.py
ofa/nas/accuracy_predictor/__init__.py
ofa/nas/accuracy_predictor/acc_dataset.py
ofa/nas/accuracy_predictor/acc_predictor.py
ofa/nas/accuracy_predictor/arch_encoder.py
ofa/nas/efficiency_predictor/__init__.py
ofa/nas/efficiency_predictor/latency_lookup_table.py
ofa/nas/search_algorithm/__init__.py
ofa/nas/search_algorithm/evolution.py
ofa/tutorial/__init__.py
ofa/tutorial/accuracy_predictor.py
ofa/tutorial/evolution_finder.py
ofa/tutorial/flops_table.py
ofa/tutorial/imagenet_eval_helper.py
ofa/tutorial/latency_table.py
ofa/utils/__init__.py
ofa/utils/common_tools.py
ofa/utils/flops_counter.py
ofa/utils/layers.py
ofa-0.1.0.post202307202001.dist-info/LICENSE
ofa-0.1.0.post202307202001.dist-info/METADATA
ofa-0.1.0.post202307202001.dist-info/WHEEL
ofa-0.1.0.post202307202001.dist-info/top_level.txt
ofa-0.1.0.post202307202001.dist-info/zip-safe
ofa-0.1.0.post202307202001.dist-info/RECORD
