Metadata-Version: 2.1
Name: ofa
Version: 0.1.0.post202307202001
Summary: Once for All: Train One Network and Specialize it for Efficient Deployment.
Home-page: https://github.com/mit-han-lab/once-for-all
Author: MTI HAN LAB 
Author-email: hcai.hm@gmail.com
License: MIT
Classifier: Programming Language :: Python :: 3
License-File: LICENSE
Requires-Dist: torch
